[{"Points":[{"X":11.25,"Y":5.0},{"X":9.75,"Y":4.5},{"X":7.5,"Y":9.0},{"X":0.5,"Y":9.0},{"X":0.5,"Y":5.0}]},{"Points":[{"X":11.25,"Y":5.0},{"X":9.75,"Y":4.5},{"X":5.25,"Y":4.5},{"X":3.75,"Y":5.0},{"X":0.5,"Y":5.0}]},{"Points":[{"X":11.25,"Y":5.0},{"X":9.75,"Y":4.5},{"X":7.5,"Y":1.0},{"X":0.5,"Y":1.0},{"X":0.5,"Y":5.0}]},{"Points":[{"X":11.25,"Y":5.0},{"X":9.75,"Y":4.5},{"X":7.5,"Y":9.0},{"X":0.5,"Y":9.0},{"X":0.5,"Y":5.0}]},{"Points":[{"X":11.25,"Y":5.0},{"X":9.75,"Y":4.5},{"X":7.5,"Y":9.0},{"X":0.5,"Y":9.0},{"X":0.5,"Y":5.0}]},{"Points":[{"X":11.25,"Y":5.0},{"X":9.75,"Y":4.5},{"X":5.25,"Y":4.5},{"X":3.75,"Y":5.0},{"X":0.5,"Y":5.0}]},{"Points":[{"X":11.25,"Y":5.0},{"X":9.75,"Y":4.5},{"X":7.5,"Y":9.0},{"X":0.5,"Y":9.0},{"X":0.5,"Y":5.0}]},{"Points":[{"X":11.25,"Y":5.0},{"X":9.75,"Y":4.5},{"X":7.5,"Y":9.0},{"X":0.5,"Y":9.0},{"X":0.5,"Y":5.0}]},{"Points":[{"X":11.25,"Y":5.0},{"X":9.75,"Y":4.5},{"X":5.25,"Y":4.5},{"X":3.75,"Y":5.0},{"X":0.5,"Y":5.0}]},{"Points":[{"X":11.25,"Y":5.0},{"X":9.75,"Y":4.5},{"X":7.5,"Y":9.0},{"X":0.5,"Y":9.0},{"X":0.5,"Y":5.0}]},{"Points":[{"X":11.25,"Y":5.0},{"X":9.75,"Y":4.5},{"X":7.5,"Y":1.0},{"X":0.5,"Y":1.0},{"X":0.5,"Y":5.0}]},{"Points":[{"X":11.25,"Y":5.0},{"X":9.75,"Y":4.5},{"X":7.5,"Y":1.0},{"X":0.5,"Y":1.0},{"X":0.5,"Y":5.0}]},{"Points":[{"X":11.25,"Y":5.0},{"X":9.75,"Y":4.5},{"X":7.5,"Y":1.0},{"X":0.5,"Y":1.0},{"X":0.5,"Y":5.0}]},{"Points":[{"X":11.25,"Y":5.0},{"X":9.75,"Y":4.5},{"X":5.25,"Y":4.5},{"X":3.75,"Y":5.0},{"X":0.5,"Y":5.0}]},{"Points":[{"X":11.25,"Y":5.0},{"X":9.75,"Y":4.5},{"X":5.25,"Y":4.5},{"X":3.75,"Y":5.0},{"X":0.5,"Y":5.0}]},{"Points":[{"X":11.25,"Y":5.0},{"X":9.75,"Y":4.5},{"X":7.5,"Y":1.0},{"X":0.5,"Y":1.0},{"X":0.5,"Y":5.0}]},{"Points":[{"X":11.25,"Y":5.0},{"X":9.75,"Y":4.5},{"X":5.25,"Y":4.5},{"X":3.75,"Y":5.0},{"X":0.5,"Y":5.0}]},{"Points":[{"X":11.25,"Y":5.0},{"X":9.75,"Y":4.5},{"X":7.5,"Y":9.0},{"X":0.5,"Y":9.0},{"X":0.5,"Y":5.0}]},{"Points":[{"X":11.25,"Y":5.0},{"X":9.75,"Y":4.5},{"X":7.5,"Y":1.0},{"X":0.5,"Y":1.0},{"X":0.5,"Y":5.0}]},{"Points":[{"X":11.25,"Y":5.0},{"X":9.75,"Y":4.5},{"X":7.5,"Y":1.0},{"X":0.5,"Y":1.0},{"X":0.5,"Y":5.0}]},{"Points":[{"X":11.25,"Y":5.0},{"X":9.75,"Y":4.5},{"X":5.25,"Y":4.5},{"X":3.75,"Y":5.0},{"X":0.5,"Y":5.0}]},{"Points":[{"X":11.25,"Y":5.0},{"X":9.75,"Y":4.5},{"X":7.5,"Y":9.0},{"X":0.5,"Y":9.0},{"X":0.5,"Y":5.0}]},{"Points":[{"X":11.25,"Y":5.0},{"X":9.75,"Y":4.5},{"X":7.5,"Y":9.0},{"X":0.5,"Y":9.0},{"X":0.5,"Y":5.0}]},{"Points":[{"X":11.25,"Y":5.0},{"X":9.75,"Y":4.5},{"X":5.25,"Y":4.5},{"X":3.75,"Y":5.0},{"X":0.5,"Y":5.0}]},{"Points":[{"X":11.25,"Y":5.0},{"X":9.75,"Y":4.5},{"X":7.5,"Y":1.0},{"X":0.5,"Y":1.0},{"X":0.5,"Y":5.0}]},{"Points":[{"X":11.25,"Y":5.0},{"X":9.75,"Y":4.5},{"X":5.25,"Y":4.5},{"X":3.75,"Y":5.0},{"X":0.5,"Y":5.0}]},{"Points":[{"X":11.25,"Y":5.0},{"X":9.75,"Y":4.5},{"X":7.5,"Y":1.0},{"X":0.5,"Y":1.0},{"X":0.5,"Y":5.0}]},{"Points":[{"X":11.25,"Y":5.0},{"X":9.75,"Y":4.5},{"X":7.5,"Y":9.0},{"X":0.5,"Y":9.0},{"X":0.5,"Y":5.0}]},{"Points":[{"X":11.25,"Y":5.0},{"X":9.75,"Y":4.5},{"X":5.25,"Y":4.5},{"X":3.75,"Y":5.0},{"X":0.5,"Y":5.0}]},{"Points":[{"X":11.25,"Y":5.0},{"X":9.75,"Y":4.5},{"X":7.5,"Y":1.0},{"X":0.5,"Y":1.0},{"X":0.5,"Y":5.0}]},{"Points":[{"X":11.25,"Y":5.0},{"X":9.75,"Y":4.5},{"X":5.25,"Y":4.5},{"X":3.75,"Y":5.0},{"X":0.5,"Y":5.0}]},{"Points":[{"X":11.25,"Y":5.0},{"X":9.75,"Y":4.5},{"X":7.5,"Y":9.0},{"X":0.5,"Y":9.0},{"X":0.5,"Y":5.0}]},{"Points":[{"X":11.25,"Y":5.0},{"X":9.75,"Y":4.5},{"X":7.5,"Y":1.0},{"X":0.5,"Y":1.0},{"X":0.5,"Y":5.0}]},{"Points":[{"X":11.25,"Y":5.0},{"X":9.75,"Y":4.5},{"X":7.5,"Y":1.0},{"X":0.5,"Y":1.0},{"X":0.5,"Y":5.0}]},{"Points":[{"X":11.25,"Y":5.0},{"X":9.75,"Y":4.5},{"X":5.25,"Y":4.5},{"X":3.75,"Y":5.0},{"X":0.5,"Y":5.0}]},{"Points":[{"X":11.25,"Y":5.0},{"X":9.75,"Y":4.5},{"X":7.5,"Y":9.0},{"X":0.5,"Y":9.0},{"X":0.5,"Y":5.0}]},{"Points":[{"X":11.25,"Y":5.0},{"X":9.75,"Y":4.5},{"X":7.5,"Y":9.0},{"X":0.5,"Y":9.0},{"X":0.5,"Y":5.0}]},{"Points":[{"X":11.25,"Y":5.0},{"X":9.75,"Y":4.5},{"X":5.25,"Y":4.5},{"X":3.75,"Y":5.0},{"X":0.5,"Y":5.0}]},{"Points":[{"X":11.25,"Y":5.0},{"X":9.75,"Y":4.5},{"X":7.5,"Y":1.0},{"X":0.5,"Y":1.0},{"X":0.5,"Y":5.0}]},{"Points":[{"X":11.25,"Y":5.0},{"X":9.75,"Y":4.5},{"X":5.25,"Y":4.5},{"X":3.75,"Y":5.0},{"X":0.5,"Y":5.0}]},{"Points":[{"X":11.25,"Y":5.0},{"X":9.75,"Y":4.5},{"X":7.5,"Y":1.0},{"X":0.5,"Y":1.0},{"X":0.5,"Y":5.0}]},{"Points":[{"X":11.25,"Y":5.0},{"X":9.75,"Y":4.5},{"X":7.5,"Y":9.0},{"X":0.5,"Y":9.0},{"X":0.5,"Y":5.0}]},{"Points":[{"X":11.25,"Y":5.0},{"X":9.75,"Y":4.5},{"X":7.5,"Y":1.0},{"X":0.5,"Y":1.0},{"X":0.5,"Y":5.0}]},{"Points":[{"X":11.25,"Y":5.0},{"X":9.75,"Y":4.5},{"X":7.5,"Y":9.0},{"X":0.5,"Y":9.0},{"X":0.5,"Y":5.0}]},{"Points":[{"X":11.25,"Y":5.0},{"X":9.75,"Y":4.5},{"X":5.25,"Y":4.5},{"X":3.75,"Y":5.0},{"X":0.5,"Y":5.0}]},{"Points":[{"X":11.25,"Y":5.0},{"X":9.75,"Y":4.5},{"X":7.5,"Y":1.0},{"X":0.5,"Y":1.0},{"X":0.5,"Y":5.0}]},{"Points":[{"X":11.25,"Y":5.0},{"X":9.75,"Y":4.5},{"X":5.25,"Y":4.5},{"X":3.75,"Y":5.0},{"X":0.5,"Y":5.0}]},{"Points":[{"X":11.25,"Y":5.0},{"X":9.75,"Y":4.5},{"X":7.5,"Y":9.0},{"X":0.5,"Y":9.0},{"X":0.5,"Y":5.0}]},{"Points":[{"X":11.25,"Y":5.0},{"X":9.75,"Y":4.5},{"X":7.5,"Y":1.0},{"X":0.5,"Y":1.0},{"X":0.5,"Y":5.0}]},{"Points":[{"X":11.25,"Y":5.0},{"X":9.75,"Y":4.5},{"X":7.5,"Y":1.0},{"X":0.5,"Y":1.0},{"X":0.5,"Y":5.0}]},{"Points":[{"X":11.25,"Y":5.0},{"X":9.75,"Y":4.5},{"X":5.25,"Y":4.5},{"X":3.75,"Y":5.0},{"X":0.5,"Y":5.0}]},{"Points":[{"X":11.25,"Y":5.0},{"X":9.75,"Y":4.5},{"X":7.5,"Y":9.0},{"X":0.5,"Y":9.0},{"X":0.5,"Y":5.0}]},{"Points":[{"X":11.25,"Y":5.0},{"X":9.75,"Y":4.5},{"X":7.5,"Y":9.0},{"X":0.5,"Y":9.0},{"X":0.5,"Y":5.0}]},{"Points":[{"X":11.25,"Y":5.0},{"X":9.75,"Y":4.5},{"X":5.25,"Y":4.5},{"X":3.75,"Y":5.0},{"X":0.5,"Y":5.0}]},{"Points":[{"X":11.25,"Y":5.0},{"X":9.75,"Y":4.5},{"X":7.5,"Y":1.0},{"X":0.5,"Y":1.0},{"X":0.5,"Y":5.0}]},{"Points":[{"X":11.25,"Y":5.0},{"X":9.75,"Y":4.5},{"X":5.25,"Y":4.5},{"X":3.75,"Y":5.0},{"X":0.5,"Y":5.0}]},{"Points":[{"X":11.25,"Y":5.0},{"X":9.75,"Y":4.5},{"X":7.5,"Y":1.0},{"X":0.5,"Y":1.0},{"X":0.5,"Y":5.0}]},{"Points":[{"X":11.25,"Y":5.0},{"X":9.75,"Y":4.5},{"X":7.5,"Y":9.0},{"X":0.5,"Y":9.0},{"X":0.5,"Y":5.0}]},{"Points":[{"X":11.25,"Y":5.0},{"X":9.75,"Y":4.5},{"X":7.5,"Y":1.0},{"X":0.5,"Y":1.0},{"X":0.5,"Y":5.0}]},{"Points":[{"X":11.25,"Y":5.0},{"X":9.75,"Y":4.5},{"X":7.5,"Y":9.0},{"X":0.5,"Y":9.0},{"X":0.5,"Y":5.0}]},{"Points":[{"X":11.25,"Y":5.0},{"X":9.75,"Y":4.5},{"X":5.25,"Y":4.5},{"X":3.75,"Y":5.0},{"X":0.5,"Y":5.0}]},{"Points":[{"X":11.25,"Y":5.0},{"X":9.75,"Y":4.5},{"X":7.5,"Y":9.0},{"X":0.5,"Y":9.0},{"X":0.5,"Y":5.0}]},{"Points":[{"X":11.25,"Y":5.0},{"X":9.75,"Y":4.5},{"X":7.5,"Y":1.0},{"X":0.5,"Y":1.0},{"X":0.5,"Y":5.0}]},{"Points":[{"X":11.25,"Y":5.0},{"X":9.75,"Y":4.5},{"X":7.5,"Y":1.0},{"X":0.5,"Y":1.0},{"X":0.5,"Y":5.0}]},{"Points":[{"X":11.25,"Y":5.0},{"X":9.75,"Y":4.5},{"X":5.25,"Y":4.5},{"X":3.75,"Y":5.0},{"X":0.5,"Y":5.0}]},{"Points":[{"X":11.25,"Y":5.0},{"X":9.75,"Y":4.5},{"X":7.5,"Y":1.0},{"X":0.5,"Y":1.0},{"X":0.5,"Y":5.0}]},{"Points":[{"X":11.25,"Y":5.0},{"X":9.75,"Y":4.5},{"X":5.25,"Y":4.5},{"X":3.75,"Y":5.0},{"X":0.5,"Y":5.0}]},{"Points":[{"X":11.25,"Y":5.0},{"X":9.75,"Y":4.5},{"X":7.5,"Y":9.0},{"X":0.5,"Y":9.0},{"X":0.5,"Y":5.0}]},{"Points":[{"X":11.25,"Y":5.0},{"X":9.75,"Y":4.5},{"X":7.5,"Y":1.0},{"X":0.5,"Y":1.0},{"X":0.5,"Y":5.0}]},{"Points":[{"X":11.25,"Y":5.0},{"X":9.75,"Y":4.5},{"X":7.5,"Y":1.0},{"X":0.5,"Y":1.0},{"X":0.5,"Y":5.0}]},{"Points":[{"X":11.25,"Y":5.0},{"X":9.75,"Y":4.5},{"X":5.25,"Y":4.5},{"X":3.75,"Y":5.0},{"X":0.5,"Y":5.0}]},{"Points":[{"X":11.25,"Y":5.0},{"X":9.75,"Y":4.5},{"X":7.5,"Y":9.0},{"X":0.5,"Y":9.0},{"X":0.5,"Y":5.0}]},{"Points":[{"X":11.25,"Y":5.0},{"X":9.75,"Y":4.5},{"X":7.5,"Y":9.0},{"X":0.5,"Y":9.0},{"X":0.5,"Y":5.0}]},{"Points":[{"X":11.25,"Y":5.0},{"X":9.75,"Y":4.5},{"X":5.25,"Y":4.5},{"X":3.75,"Y":5.0},{"X":0.5,"Y":5.0}]},{"Points":[{"X":11.25,"Y":5.0},{"X":9.75,"Y":4.5},{"X":7.5,"Y":1.0},{"X":0.5,"Y":1.0},{"X":0.5,"Y":5.0}]},{"Points":[{"X":11.25,"Y":5.0},{"X":9.75,"Y":4.5},{"X":5.25,"Y":4.5},{"X":3.75,"Y":5.0},{"X":0.5,"Y":5.0}]},{"Points":[{"X":11.25,"Y":5.0},{"X":9.75,"Y":4.5},{"X":7.5,"Y":1.0},{"X":0.5,"Y":1.0},{"X":0.5,"Y":5.0}]},{"Points":[{"X":11.25,"Y":5.0},{"X":9.75,"Y":4.5},{"X":7.5,"Y":9.0},{"X":0.5,"Y":9.0},{"X":0.5,"Y":5.0}]},{"Points":[{"X":11.25,"Y":5.0},{"X":9.75,"Y":4.5},{"X":7.5,"Y":1.0},{"X":0.5,"Y":1.0},{"X":0.5,"Y":5.0}]},{"Points":[{"X":11.25,"Y":5.0},{"X":9.75,"Y":4.5},{"X":7.5,"Y":9.0},{"X":0.5,"Y":9.0},{"X":0.5,"Y":5.0}]},{"Points":[{"X":11.25,"Y":5.0},{"X":9.75,"Y":4.5},{"X":5.25,"Y":4.5},{"X":3.75,"Y":5.0},{"X":0.5,"Y":5.0}]},{"Points":[{"X":11.25,"Y":5.0},{"X":9.75,"Y":4.5},{"X":5.25,"Y":4.5},{"X":3.75,"Y":5.0},{"X":0.5,"Y":5.0}]},{"Points":[{"X":11.25,"Y":5.0},{"X":9.75,"Y":4.5},{"X":7.5,"Y":1.0},{"X":0.5,"Y":1.0},{"X":0.5,"Y":5.0}]},{"Points":[{"X":11.25,"Y":5.0},{"X":9.75,"Y":4.5},{"X":5.25,"Y":4.5},{"X":3.75,"Y":5.0},{"X":0.5,"Y":5.0}]},{"Points":[{"X":11.25,"Y":5.0},{"X":9.75,"Y":4.5},{"X":7.5,"Y":9.0},{"X":0.5,"Y":9.0},{"X":0.5,"Y":5.0}]},{"Points":[{"X":11.25,"Y":5.0},{"X":9.75,"Y":4.5},{"X":7.5,"Y":1.0},{"X":0.5,"Y":1.0},{"X":0.5,"Y":5.0}]},{"Points":[{"X":11.25,"Y":5.0},{"X":9.75,"Y":4.5},{"X":7.5,"Y":1.0},{"X":0.5,"Y":1.0},{"X":0.5,"Y":5.0}]},{"Points":[{"X":11.25,"Y":5.0},{"X":9.75,"Y":4.5},{"X":5.25,"Y":4.5},{"X":3.75,"Y":5.0},{"X":0.5,"Y":5.0}]},{"Points":[{"X":11.25,"Y":5.0},{"X":9.75,"Y":4.5},{"X":7.5,"Y":9.0},{"X":0.5,"Y":9.0},{"X":0.5,"Y":5.0}]},{"Points":[{"X":11.25,"Y":5.0},{"X":9.75,"Y":4.5},{"X":7.5,"Y":9.0},{"X":0.5,"Y":9.0},{"X":0.5,"Y":5.0}]},{"Points":[{"X":11.25,"Y":5.0},{"X":9.75,"Y":4.5},{"X":5.25,"Y":4.5},{"X":3.75,"Y":5.0},{"X":0.5,"Y":5.0}]},{"Points":[{"X":11.25,"Y":5.0},{"X":9.75,"Y":4.5},{"X":7.5,"Y":1.0},{"X":0.5,"Y":1.0},{"X":0.5,"Y":5.0}]},{"Points":[{"X":11.25,"Y":5.0},{"X":9.75,"Y":4.5},{"X":5.25,"Y":4.5},{"X":3.75,"Y":5.0},{"X":0.5,"Y":5.0}]},{"Points":[{"X":11.25,"Y":5.0},{"X":9.75,"Y":4.5},{"X":7.5,"Y":1.0},{"X":0.5,"Y":1.0},{"X":0.5,"Y":5.0}]},{"Points":[{"X":11.25,"Y":5.0},{"X":9.75,"Y":4.5},{"X":5.25,"Y":4.5},{"X":3.75,"Y":5.0},{"X":0.5,"Y":5.0}]},{"Points":[{"X":11.25,"Y":5.0},{"X":9.75,"Y":4.5},{"X":7.5,"Y":1.0},{"X":0.5,"Y":1.0},{"X":0.5,"Y":5.0}]},{"Points":[{"X":11.25,"Y":5.0},{"X":9.75,"Y":4.5},{"X":5.25,"Y":4.5},{"X":3.75,"Y":5.0},{"X":0.5,"Y":5.0}]},{"Points":[{"X":11.25,"Y":5.0},{"X":9.75,"Y":4.5},{"X":7.5,"Y":9.0},{"X":0.5,"Y":9.0},{"X":0.5,"Y":5.0}]},{"Points":[{"X":11.25,"Y":5.0},{"X":9.75,"Y":4.5},{"X":7.5,"Y":1.0},{"X":0.5,"Y":1.0},{"X":0.5,"Y":5.0}]},{"Points":[{"X":11.25,"Y":5.0},{"X":9.75,"Y":4.5},{"X":7.5,"Y":1.0},{"X":0.5,"Y":1.0},{"X":0.5,"Y":5.0}]},{"Points":[{"X":11.25,"Y":5.0},{"X":9.75,"Y":4.5},{"X":5.25,"Y":4.5},{"X":3.75,"Y":5.0},{"X":0.5,"Y":5.0}]},{"Points":[{"X":11.25,"Y":5.0},{"X":9.75,"Y":4.5},{"X":7.5,"Y":9.0},{"X":0.5,"Y":9.0},{"X":0.5,"Y":5.0}]},{"Points":[{"X":11.25,"Y":5.0},{"X":9.75,"Y":4.5},{"X":7.5,"Y":9.0},{"X":0.5,"Y":9.0},{"X":0.5,"Y":5.0}]},{"Points":[{"X":11.25,"Y":5.0},{"X":9.75,"Y":4.5},{"X":5.25,"Y":4.5},{"X":3.75,"Y":5.0},{"X":0.5,"Y":5.0}]},{"Points":[{"X":11.25,"Y":5.0},{"X":9.75,"Y":4.5},{"X":7.5,"Y":1.0},{"X":0.5,"Y":1.0},{"X":0.5,"Y":5.0}]},{"Points":[{"X":11.25,"Y":5.0},{"X":9.75,"Y":4.5},{"X":5.25,"Y":4.5},{"X":3.75,"Y":5.0},{"X":0.5,"Y":5.0}]},{"Points":[{"X":11.25,"Y":5.0},{"X":9.75,"Y":4.5},{"X":7.5,"Y":1.0},{"X":0.5,"Y":1.0},{"X":0.5,"Y":5.0}]},{"Points":[{"X":11.25,"Y":5.0},{"X":9.75,"Y":4.5},{"X":7.5,"Y":9.0},{"X":0.5,"Y":9.0},{"X":0.5,"Y":5.0}]},{"Points":[{"X":11.25,"Y":5.0},{"X":9.75,"Y":4.5},{"X":7.5,"Y":1.0},{"X":0.5,"Y":1.0},{"X":0.5,"Y":5.0}]},{"Points":[{"X":11.25,"Y":5.0},{"X":9.75,"Y":4.5},{"X":7.5,"Y":9.0},{"X":0.5,"Y":9.0},{"X":0.5,"Y":5.0}]},{"Points":[{"X":11.25,"Y":5.0},{"X":9.75,"Y":4.5},{"X":5.25,"Y":4.5},{"X":3.75,"Y":5.0},{"X":0.5,"Y":5.0}]},{"Points":[{"X":11.25,"Y":5.0},{"X":9.75,"Y":4.5},{"X":7.5,"Y":9.0},{"X":0.5,"Y":9.0},{"X":0.5,"Y":5.0}]},{"Points":[{"X":11.25,"Y":5.0},{"X":9.75,"Y":4.5},{"X":7.5,"Y":1.0},{"X":0.5,"Y":1.0},{"X":0.5,"Y":5.0}]},{"Points":[{"X":11.25,"Y":5.0},{"X":9.75,"Y":4.5},{"X":7.5,"Y":1.0},{"X":0.5,"Y":1.0},{"X":0.5,"Y":5.0}]},{"Points":[{"X":11.25,"Y":5.0},{"X":9.75,"Y":4.5},{"X":5.25,"Y":4.5},{"X":3.75,"Y":5.0},{"X":0.5,"Y":5.0}]},{"Points":[{"X":11.25,"Y":5.0},{"X":9.75,"Y":4.5},{"X":7.5,"Y":1.0},{"X":0.5,"Y":1.0},{"X":0.5,"Y":5.0}]},{"Points":[{"X":11.25,"Y":5.0},{"X":9.75,"Y":4.5},{"X":5.25,"Y":4.5},{"X":3.75,"Y":5.0},{"X":0.5,"Y":5.0}]},{"Points":[{"X":11.25,"Y":5.0},{"X":9.75,"Y":4.5},{"X":7.5,"Y":9.0},{"X":0.5,"Y":9.0},{"X":0.5,"Y":5.0}]},{"Points":[{"X":11.25,"Y":5.0},{"X":9.75,"Y":4.5},{"X":7.5,"Y":1.0},{"X":0.5,"Y":1.0},{"X":0.5,"Y":5.0}]},{"Points":[{"X":11.25,"Y":5.0},{"X":9.75,"Y":4.5},{"X":7.5,"Y":1.0},{"X":0.5,"Y":1.0},{"X":0.5,"Y":5.0}]},{"Points":[{"X":11.25,"Y":5.0},{"X":9.75,"Y":4.5},{"X":5.25,"Y":4.5},{"X":3.75,"Y":5.0},{"X":0.5,"Y":5.0}]},{"Points":[{"X":11.25,"Y":5.0},{"X":9.75,"Y":4.5},{"X":7.5,"Y":9.0},{"X":0.5,"Y":9.0},{"X":0.5,"Y":5.0}]},{"Points":[{"X":11.25,"Y":5.0},{"X":9.75,"Y":4.5},{"X":7.5,"Y":1.0},{"X":0.5,"Y":1.0},{"X":0.5,"Y":5.0}]},{"Points":[{"X":11.25,"Y":5.0},{"X":9.75,"Y":4.5},{"X":5.25,"Y":4.5},{"X":3.75,"Y":5.0},{"X":0.5,"Y":5.0}]},{"Points":[{"X":11.25,"Y":5.0},{"X":9.75,"Y":4.5},{"X":5.25,"Y":4.5},{"X":3.75,"Y":5.0},{"X":0.5,"Y":5.0}]},{"Points":[{"X":11.25,"Y":5.0},{"X":9.75,"Y":4.5},{"X":7.5,"Y":9.0},{"X":0.5,"Y":9.0},{"X":0.5,"Y":5.0}]},{"Points":[{"X":11.25,"Y":5.0},{"X":9.75,"Y":4.5},{"X":5.25,"Y":4.5},{"X":3.75,"Y":5.0},{"X":0.5,"Y":5.0}]},{"Points":[{"X":11.25,"Y":5.0},{"X":9.75,"Y":4.5},{"X":7.5,"Y":1.0},{"X":0.5,"Y":1.0},{"X":0.5,"Y":5.0}]},{"Points":[{"X":11.25,"Y":5.0},{"X":9.75,"Y":4.5},{"X":5.25,"Y":4.5},{"X":3.75,"Y":5.0},{"X":0.5,"Y":5.0}]},{"Points":[{"X":11.25,"Y":5.0},{"X":9.75,"Y":4.5},{"X":7.5,"Y":9.0},{"X":0.5,"Y":9.0},{"X":0.5,"Y":5.0}]},{"Points":[{"X":11.25,"Y":5.0},{"X":9.75,"Y":4.5},{"X":7.5,"Y":9.0},{"X":0.5,"Y":9.0},{"X":0.5,"Y":5.0}]},{"Points":[{"X":11.25,"Y":5.0},{"X":9.75,"Y":4.5},{"X":7.5,"Y":9.0},{"X":0.5,"Y":9.0},{"X":0.5,"Y":5.0}]},{"Points":[{"X":11.25,"Y":5.0},{"X":9.75,"Y":4.5},{"X":5.25,"Y":4.5},{"X":3.75,"Y":5.0},{"X":0.5,"Y":5.0}]},{"Points":[{"X":11.25,"Y":5.0},{"X":9.75,"Y":4.5},{"X":7.5,"Y":1.0},{"X":0.5,"Y":1.0},{"X":0.5,"Y":5.0}]},{"Points":[{"X":11.25,"Y":5.0},{"X":9.75,"Y":4.5},{"X":7.5,"Y":1.0},{"X":0.5,"Y":1.0},{"X":0.5,"Y":5.0}]},{"Points":[{"X":11.25,"Y":5.0},{"X":9.75,"Y":4.5},{"X":7.5,"Y":1.0},{"X":0.5,"Y":1.0},{"X":0.5,"Y":5.0}]},{"Points":[{"X":11.25,"Y":5.0},{"X":9.75,"Y":4.5},{"X":7.5,"Y":9.0},{"X":0.5,"Y":9.0},{"X":0.5,"Y":5.0}]},{"Points":[{"X":11.25,"Y":5.0},{"X":9.75,"Y":4.5},{"X":7.5,"Y":1.0},{"X":0.5,"Y":1.0},{"X":0.5,"Y":5.0}]},{"Points":[{"X":11.25,"Y":5.0},{"X":9.75,"Y":4.5},{"X":5.25,"Y":4.5},{"X":3.75,"Y":5.0},{"X":0.5,"Y":5.0}]},{"Points":[{"X":11.25,"Y":5.0},{"X":9.75,"Y":4.5},{"X":5.25,"Y":4.5},{"X":3.75,"Y":5.0},{"X":0.5,"Y":5.0}]},{"Points":[{"X":11.25,"Y":5.0},{"X":9.75,"Y":4.5},{"X":7.5,"Y":9.0},{"X":0.5,"Y":9.0},{"X":0.5,"Y":5.0}]},{"Points":[{"X":11.25,"Y":5.0},{"X":9.75,"Y":4.5},{"X":5.25,"Y":4.5},{"X":3.75,"Y":5.0},{"X":0.5,"Y":5.0}]},{"Points":[{"X":11.25,"Y":5.0},{"X":9.75,"Y":4.5},{"X":7.5,"Y":1.0},{"X":0.5,"Y":1.0},{"X":0.5,"Y":5.0}]},{"Points":[{"X":11.25,"Y":5.0},{"X":9.75,"Y":4.5},{"X":7.5,"Y":9.0},{"X":0.5,"Y":9.0},{"X":0.5,"Y":5.0}]},{"Points":[{"X":11.25,"Y":5.0},{"X":9.75,"Y":4.5},{"X":7.5,"Y":1.0},{"X":0.5,"Y":1.0},{"X":0.5,"Y":5.0}]},{"Points":[{"X":11.25,"Y":5.0},{"X":9.75,"Y":4.5},{"X":5.25,"Y":4.5},{"X":3.75,"Y":5.0},{"X":0.5,"Y":5.0}]},{"Points":[{"X":11.25,"Y":5.0},{"X":9.75,"Y":4.5},{"X":5.25,"Y":4.5},{"X":3.75,"Y":5.0},{"X":0.5,"Y":5.0}]},{"Points":[{"X":11.25,"Y":5.0},{"X":9.75,"Y":4.5},{"X":7.5,"Y":9.0},{"X":0.5,"Y":9.0},{"X":0.5,"Y":5.0}]},{"Points":[{"X":11.25,"Y":5.0},{"X":9.75,"Y":4.5},{"X":5.25,"Y":4.5},{"X":3.75,"Y":5.0},{"X":0.5,"Y":5.0}]},{"Points":[{"X":11.25,"Y":5.0},{"X":9.75,"Y":4.5},{"X":7.5,"Y":1.0},{"X":0.5,"Y":1.0},{"X":0.5,"Y":5.0}]},{"Points":[{"X":11.25,"Y":5.0},{"X":9.75,"Y":4.5},{"X":5.25,"Y":4.5},{"X":3.75,"Y":5.0},{"X":0.5,"Y":5.0}]},{"Points":[{"X":11.25,"Y":5.0},{"X":9.75,"Y":4.5},{"X":7.5,"Y":9.0},{"X":0.5,"Y":9.0},{"X":0.5,"Y":5.0}]},{"Points":[{"X":11.25,"Y":5.0},{"X":9.75,"Y":4.5},{"X":7.5,"Y":9.0},{"X":0.5,"Y":9.0},{"X":0.5,"Y":5.0}]},{"Points":[{"X":11.25,"Y":5.0},{"X":9.75,"Y":4.5},{"X":7.5,"Y":9.0},{"X":0.5,"Y":9.0},{"X":0.5,"Y":5.0}]},{"Points":[{"X":11.25,"Y":5.0},{"X":9.75,"Y":4.5},{"X":5.25,"Y":4.5},{"X":3.75,"Y":5.0},{"X":0.5,"Y":5.0}]},{"Points":[{"X":11.25,"Y":5.0},{"X":9.75,"Y":4.5},{"X":7.5,"Y":9.0},{"X":0.5,"Y":9.0},{"X":0.5,"Y":5.0}]},{"Points":[{"X":11.25,"Y":5.0},{"X":9.75,"Y":4.5},{"X":7.5,"Y":1.0},{"X":0.5,"Y":1.0},{"X":0.5,"Y":5.0}]},{"Points":[{"X":11.25,"Y":5.0},{"X":9.75,"Y":4.5},{"X":5.25,"Y":4.5},{"X":3.75,"Y":5.0},{"X":0.5,"Y":5.0}]},{"Points":[{"X":11.25,"Y":5.0},{"X":9.75,"Y":4.5},{"X":5.25,"Y":4.5},{"X":3.75,"Y":5.0},{"X":0.5,"Y":5.0}]},{"Points":[{"X":11.25,"Y":5.0},{"X":9.75,"Y":4.5},{"X":7.5,"Y":9.0},{"X":0.5,"Y":9.0},{"X":0.5,"Y":5.0}]},{"Points":[{"X":11.25,"Y":5.0},{"X":9.75,"Y":4.5},{"X":5.25,"Y":4.5},{"X":3.75,"Y":5.0},{"X":0.5,"Y":5.0}]},{"Points":[{"X":11.25,"Y":5.0},{"X":9.75,"Y":4.5},{"X":7.5,"Y":1.0},{"X":0.5,"Y":1.0},{"X":0.5,"Y":5.0}]},{"Points":[{"X":11.25,"Y":5.0},{"X":9.75,"Y":4.5},{"X":5.25,"Y":4.5},{"X":3.75,"Y":5.0},{"X":0.5,"Y":5.0}]},{"Points":[{"X":11.25,"Y":5.0},{"X":9.75,"Y":4.5},{"X":7.5,"Y":9.0},{"X":0.5,"Y":9.0},{"X":0.5,"Y":5.0}]},{"Points":[{"X":11.25,"Y":5.0},{"X":9.75,"Y":4.5},{"X":7.5,"Y":9.0},{"X":0.5,"Y":9.0},{"X":0.5,"Y":5.0}]},{"Points":[{"X":11.25,"Y":5.0},{"X":9.75,"Y":4.5},{"X":7.5,"Y":9.0},{"X":0.5,"Y":9.0},{"X":0.5,"Y":5.0}]},{"Points":[{"X":11.25,"Y":5.0},{"X":9.75,"Y":4.5},{"X":5.25,"Y":4.5},{"X":3.75,"Y":5.0},{"X":0.5,"Y":5.0}]},{"Points":[{"X":11.25,"Y":5.0},{"X":9.75,"Y":4.5},{"X":7.5,"Y":1.0},{"X":0.5,"Y":1.0},{"X":0.5,"Y":5.0}]},{"Points":[{"X":11.25,"Y":5.0},{"X":9.75,"Y":4.5},{"X":7.5,"Y":1.0},{"X":0.5,"Y":1.0},{"X":0.5,"Y":5.0}]},{"Points":[{"X":11.25,"Y":5.0},{"X":9.75,"Y":4.5},{"X":7.5,"Y":1.0},{"X":0.5,"Y":1.0},{"X":0.5,"Y":5.0}]}]